{
  "classname": null,
  "name": null,
  "animation": {
    "classname": null,
    "name": "AnimationManager",
    "actionlist": []
  },
  "dataScale": 1,
  "designHeight": 150,
  "designWidth": 505,
  "textures": [],
  "texturesPng": [
    "images/img_285.png",
    "GUI/image.png",
    "button/btn_150.png",
    "button/btn_184.png"
  ],
  "version": "1.5.0.0",
  "widgetTree": {
    "classname": "Panel",
    "name": null,
    "children": [
      {
        "classname": "Panel",
        "name": null,
        "children": [
          {
            "classname": "ImageView",
            "name": null,
            "children": [],
            "options": {
              "__type": "ImageViewSurrogate:#EditorCommon.JsonModel.Component.GUI",
              "classname": "ImageView",
              "name": "img_header",
              "ZOrder": 0,
              "actiontag": 7559386,
              "anchorPointX": 0,
              "anchorPointY": 0,
              "classType": "CocoStudio.EngineAdapterWrap.CSImageView",
              "colorB": 255,
              "colorG": 255,
              "colorR": 255,
              "customProperty": "",
              "flipX": false,
              "flipY": false,
              "height": 80,
              "ignoreSize": true,
              "layoutParameter": null,
              "opacity": 255,
              "positionPercentX": 0.04422442,
              "positionPercentY": 0.351598144,
              "positionType": 0,
              "rotation": 0,
              "scaleX": 0.8,
              "scaleY": 0.8,
              "sizePercentX": 0.158415839,
              "sizePercentY": 0.5479452,
              "sizeType": 0,
              "tag": 114301,
              "touchAble": false,
              "useMergedTexture": false,
              "visible": true,
              "width": 80,
              "x": 22,
              "y": 51,
              "capInsetsHeight": 1,
              "capInsetsWidth": 1,
              "capInsetsX": 0,
              "capInsetsY": 0,
              "fileName": null,
              "fileNameData": {
                "path": "GUI/image.png",
                "plistFile": "",
                "resourceType": 0
              },
              "scale9Enable": false,
              "scale9Height": 80,
              "scale9Width": 80
            }
          },
          {
            "classname": "Label",
            "name": null,
            "children": [],
            "options": {
              "__type": "LabelSurrogate:#EditorCommon.JsonModel.Component.GUI",
              "classname": "Label",
              "name": "lbl_name",
              "ZOrder": 0,
              "actiontag": 24538918,
              "anchorPointX": 0,
              "anchorPointY": 0.5,
              "classType": "CocoStudio.EngineAdapterWrap.CSLabel",
              "colorB": 255,
              "colorG": 255,
              "colorR": 0,
              "customProperty": "",
              "flipX": false,
              "flipY": false,
              "height": 27,
              "ignoreSize": true,
              "layoutParameter": null,
              "opacity": 255,
              "positionPercentX": 0.238008782,
              "positionPercentY": 0.7305934,
              "positionType": 0,
              "rotation": 0,
              "scaleX": 1,
              "scaleY": 1,
              "sizePercentX": 0.188118815,
              "sizePercentY": 0.1849315,
              "sizeType": 0,
              "tag": 114302,
              "touchAble": false,
              "useMergedTexture": false,
              "visible": true,
              "width": 103,
              "x": 120,
              "y": 106,
              "areaHeight": 0,
              "areaWidth": 0,
              "fontFile": null,
              "fontName": "微软雅黑",
              "fontSize": 20,
              "hAlignment": 0,
              "text": "LV： name",
              "touchScaleEnable": false,
              "vAlignment": 0
            }
          },
          {
            "classname": "Label",
            "name": null,
            "children": [],
            "options": {
              "__type": "LabelSurrogate:#EditorCommon.JsonModel.Component.GUI",
              "classname": "Label",
              "name": "lbl_time",
              "ZOrder": 0,
              "actiontag": 46793623,
              "anchorPointX": 0,
              "anchorPointY": 0.5,
              "classType": "CocoStudio.EngineAdapterWrap.CSLabel",
              "colorB": 230,
              "colorG": 216,
              "colorR": 173,
              "customProperty": "",
              "flipX": false,
              "flipY": false,
              "height": 27,
              "ignoreSize": true,
              "layoutParameter": null,
              "opacity": 255,
              "positionPercentX": 0.238008782,
              "positionPercentY": 0.216514677,
              "positionType": 0,
              "rotation": 0,
              "scaleX": 1,
              "scaleY": 1,
              "sizePercentX": 0.188118815,
              "sizePercentY": 0.1849315,
              "sizeType": 0,
              "tag": 114303,
              "touchAble": false,
              "useMergedTexture": false,
              "visible": true,
              "width": 64,
              "x": 120,
              "y": 31,
              "areaHeight": 0,
              "areaWidth": 0,
              "fontFile": null,
              "fontName": "微软雅黑",
              "fontSize": 20,
              "hAlignment": 0,
              "text": "23分钟",
              "touchScaleEnable": false,
              "vAlignment": 0
            }
          },
          {
            "classname": "Panel",
            "name": null,
            "children": [
              {
                "classname": "Button",
                "name": null,
                "children": [],
                "options": {
                  "__type": "ButtonSurrogate:#EditorCommon.JsonModel.Component.GUI",
                  "classname": "Button",
                  "name": "btn_del",
                  "ZOrder": 0,
                  "actiontag": 377729,
                  "anchorPointX": 0.5,
                  "anchorPointY": 0.5,
                  "classType": "CocoStudio.EngineAdapterWrap.CSButton",
                  "colorB": 255,
                  "colorG": 255,
                  "colorR": 255,
                  "customProperty": "",
                  "flipX": false,
                  "flipY": false,
                  "height": 58,
                  "ignoreSize": true,
                  "layoutParameter": null,
                  "opacity": 255,
                  "positionPercentX": 0.5,
                  "positionPercentY": 0.218723148,
                  "positionType": 0,
                  "rotation": 0,
                  "scaleX": 0.8,
                  "scaleY": 0.8,
                  "sizePercentX": 1.03,
                  "sizePercentY": 0.4,
                  "sizeType": 0,
                  "tag": 114305,
                  "touchAble": true,
                  "useMergedTexture": false,
                  "visible": true,
                  "width": 90,
                  "x": 50,
                  "y": 21,
                  "capInsetsHeight": 1,
                  "capInsetsWidth": 1,
                  "capInsetsX": 0,
                  "capInsetsY": 0,
                  "disabled": null,
                  "disabledData": {
                    "path": null,
                    "plistFile": null,
                    "resourceType": 0
                  },
                  "fontName": "微软雅黑",
                  "fontSize": 21,
                  "fontType": 0,
                  "normal": null,
                  "normalData": {
                    "path": "button/btn_150.png",
                    "plistFile": "",
                    "resourceType": 0
                  },
                  "pressed": null,
                  "pressedData": {
                    "path": null,
                    "plistFile": null,
                    "resourceType": 0
                  },
                  "scale9Enable": false,
                  "scale9Height": 58,
                  "scale9Width": 90,
                  "text": "拒绝",
                  "textColorB": 255,
                  "textColorG": 255,
                  "textColorR": 255
                }
              },
              {
                "classname": "Button",
                "name": null,
                "children": [],
                "options": {
                  "__type": "ButtonSurrogate:#EditorCommon.JsonModel.Component.GUI",
                  "classname": "Button",
                  "name": "btn_receive",
                  "ZOrder": 0,
                  "actiontag": 32088434,
                  "anchorPointX": 0.5,
                  "anchorPointY": 0.5,
                  "classType": "CocoStudio.EngineAdapterWrap.CSButton",
                  "colorB": 255,
                  "colorG": 255,
                  "colorR": 255,
                  "customProperty": "",
                  "flipX": false,
                  "flipY": false,
                  "height": 58,
                  "ignoreSize": true,
                  "layoutParameter": null,
                  "opacity": 255,
                  "positionPercentX": 0.5,
                  "positionPercentY": 0.7521213,
                  "positionType": 0,
                  "rotation": 0,
                  "scaleX": 0.8,
                  "scaleY": 0.799999952,
                  "sizePercentX": 1.03,
                  "sizePercentY": 0.4,
                  "sizeType": 0,
                  "tag": 114304,
                  "touchAble": true,
                  "useMergedTexture": false,
                  "visible": true,
                  "width": 90,
                  "x": 50,
                  "y": 75,
                  "capInsetsHeight": 1,
                  "capInsetsWidth": 1,
                  "capInsetsX": 0,
                  "capInsetsY": 0,
                  "disabled": null,
                  "disabledData": {
                    "path": null,
                    "plistFile": null,
                    "resourceType": 0
                  },
                  "fontName": "微软雅黑",
                  "fontSize": 25,
                  "fontType": 0,
                  "normal": null,
                  "normalData": {
                    "path": "button/btn_184.png",
                    "plistFile": "",
                    "resourceType": 0
                  },
                  "pressed": null,
                  "pressedData": {
                    "path": null,
                    "plistFile": null,
                    "resourceType": 0
                  },
                  "scale9Enable": false,
                  "scale9Height": 58,
                  "scale9Width": 90,
                  "text": "接受",
                  "textColorB": 255,
                  "textColorG": 255,
                  "textColorR": 255
                }
              }
            ],
            "options": {
              "__type": "PanelSurrogate:#EditorCommon.JsonModel.Component.GUI",
              "classname": "Panel",
              "name": "pnl_op",
              "ZOrder": 0,
              "actiontag": 23804665,
              "anchorPointX": 0,
              "anchorPointY": 0,
              "classType": "CocoStudio.EngineAdapterWrap.CSPanel",
              "colorB": 255,
              "colorG": 255,
              "colorR": 255,
              "customProperty": "",
              "flipX": false,
              "flipY": false,
              "height": 100,
              "ignoreSize": false,
              "layoutParameter": null,
              "opacity": 255,
              "positionPercentX": 0.7850111,
              "positionPercentY": 0.15544194,
              "positionType": 0,
              "rotation": 0,
              "scaleX": 1,
              "scaleY": 1,
              "sizePercentX": 0.1980198,
              "sizePercentY": 0.6849315,
              "sizeType": 0,
              "tag": 114307,
              "touchAble": true,
              "useMergedTexture": false,
              "visible": true,
              "width": 100,
              "x": 396,
              "y": 22,
              "adaptScreen": false,
              "backGroundImage": null,
              "backGroundImageData": null,
              "backGroundScale9Enable": false,
              "bgColorB": 255,
              "bgColorG": 200,
              "bgColorOpacity": 0,
              "bgColorR": 150,
              "bgEndColorB": 255,
              "bgEndColorG": 200,
              "bgEndColorR": 150,
              "bgStartColorB": 255,
              "bgStartColorG": 255,
              "bgStartColorR": 255,
              "capInsetsHeight": 1,
              "capInsetsWidth": 1,
              "capInsetsX": 0,
              "capInsetsY": 0,
              "clipAble": false,
              "colorType": 1,
              "layoutType": 0,
              "vectorX": 0,
              "vectorY": -0.5
            }
          },
          {
            "classname": "Panel",
            "name": null,
            "children": [
              {
                "classname": "Label",
                "name": null,
                "children": [],
                "options": {
                  "__type": "LabelSurrogate:#EditorCommon.JsonModel.Component.GUI",
                  "classname": "Label",
                  "name": "lbl_state",
                  "ZOrder": 0,
                  "actiontag": 58499828,
                  "anchorPointX": 0.5,
                  "anchorPointY": 0.5,
                  "classType": "CocoStudio.EngineAdapterWrap.CSLabel",
                  "colorB": 238,
                  "colorG": 238,
                  "colorR": 175,
                  "customProperty": "",
                  "flipX": false,
                  "flipY": false,
                  "height": 27,
                  "ignoreSize": true,
                  "layoutParameter": null,
                  "opacity": 255,
                  "positionPercentX": 0.5,
                  "positionPercentY": 0.5,
                  "positionType": 0,
                  "rotation": 0,
                  "scaleX": 1,
                  "scaleY": 1,
                  "sizePercentX": 0.6,
                  "sizePercentY": 0.27,
                  "sizeType": 0,
                  "tag": 114309,
                  "touchAble": false,
                  "useMergedTexture": false,
                  "visible": true,
                  "width": 60,
                  "x": 50,
                  "y": 50,
                  "areaHeight": 0,
                  "areaWidth": 0,
                  "fontFile": null,
                  "fontName": "微软雅黑",
                  "fontSize": 20,
                  "hAlignment": 0,
                  "text": "已拒绝",
                  "touchScaleEnable": false,
                  "vAlignment": 0
                }
              }
            ],
            "options": {
              "__type": "PanelSurrogate:#EditorCommon.JsonModel.Component.GUI",
              "classname": "Panel",
              "name": "pnl_state",
              "ZOrder": 0,
              "actiontag": 12967505,
              "anchorPointX": 0,
              "anchorPointY": 0,
              "classType": "CocoStudio.EngineAdapterWrap.CSPanel",
              "colorB": 255,
              "colorG": 255,
              "colorR": 255,
              "customProperty": "",
              "flipX": false,
              "flipY": false,
              "height": 100,
              "ignoreSize": false,
              "layoutParameter": null,
              "opacity": 255,
              "positionPercentX": 0.780693,
              "positionPercentY": 0.146404475,
              "positionType": 0,
              "rotation": 0,
              "scaleX": 1,
              "scaleY": 1,
              "sizePercentX": 0.1980198,
              "sizePercentY": 0.6849315,
              "sizeType": 0,
              "tag": 114308,
              "touchAble": true,
              "useMergedTexture": false,
              "visible": true,
              "width": 100,
              "x": 394,
              "y": 21,
              "adaptScreen": false,
              "backGroundImage": null,
              "backGroundImageData": null,
              "backGroundScale9Enable": false,
              "bgColorB": 255,
              "bgColorG": 200,
              "bgColorOpacity": 0,
              "bgColorR": 150,
              "bgEndColorB": 255,
              "bgEndColorG": 200,
              "bgEndColorR": 150,
              "bgStartColorB": 255,
              "bgStartColorG": 255,
              "bgStartColorR": 255,
              "capInsetsHeight": 1,
              "capInsetsWidth": 1,
              "capInsetsX": 0,
              "capInsetsY": 0,
              "clipAble": false,
              "colorType": 1,
              "layoutType": 0,
              "vectorX": 0,
              "vectorY": -0.5
            }
          }
        ],
        "options": {
          "__type": "PanelSurrogate:#EditorCommon.JsonModel.Component.GUI",
          "classname": "Panel",
          "name": "Panel_43",
          "ZOrder": 0,
          "actiontag": 1780790,
          "anchorPointX": 0,
          "anchorPointY": 0,
          "classType": "CocoStudio.EngineAdapterWrap.CSPanel",
          "colorB": 255,
          "colorG": 255,
          "colorR": 255,
          "customProperty": "",
          "flipX": false,
          "flipY": false,
          "height": 146,
          "ignoreSize": false,
          "layoutParameter": null,
          "opacity": 255,
          "positionPercentX": 1.80978954E-09,
          "positionPercentY": 0.0400000066,
          "positionType": 0,
          "rotation": 0,
          "scaleX": 1,
          "scaleY": 1,
          "sizePercentX": 1,
          "sizePercentY": 0.973333359,
          "sizeType": 0,
          "tag": 116503,
          "touchAble": true,
          "useMergedTexture": false,
          "visible": true,
          "width": 505,
          "x": 0,
          "y": 6,
          "adaptScreen": false,
          "backGroundImage": null,
          "backGroundImageData": {
            "path": "images/img_285.png",
            "plistFile": "",
            "resourceType": 0
          },
          "backGroundScale9Enable": true,
          "bgColorB": 255,
          "bgColorG": 200,
          "bgColorOpacity": 0,
          "bgColorR": 150,
          "bgEndColorB": 255,
          "bgEndColorG": 200,
          "bgEndColorR": 150,
          "bgStartColorB": 255,
          "bgStartColorG": 255,
          "bgStartColorR": 255,
          "capInsetsHeight": 1,
          "capInsetsWidth": 1,
          "capInsetsX": 117,
          "capInsetsY": 0,
          "clipAble": false,
          "colorType": 1,
          "layoutType": 0,
          "vectorX": 0,
          "vectorY": -0.5
        }
      }
    ],
    "options": {
      "__type": "PanelSurrogate:#EditorCommon.JsonModel.Component.GUI",
      "classname": "Panel",
      "name": "Panel_5",
      "ZOrder": 0,
      "actiontag": -1,
      "anchorPointX": 0,
      "anchorPointY": 0,
      "classType": "CocoStudio.EngineAdapterWrap.CSPanel",
      "colorB": 255,
      "colorG": 255,
      "colorR": 255,
      "customProperty": "",
      "flipX": false,
      "flipY": false,
      "height": 150,
      "ignoreSize": false,
      "layoutParameter": null,
      "opacity": 255,
      "positionPercentX": 0,
      "positionPercentY": 0,
      "positionType": 0,
      "rotation": 0,
      "scaleX": 1,
      "scaleY": 1,
      "sizePercentX": 1,
      "sizePercentY": 1,
      "sizeType": 0,
      "tag": 114300,
      "touchAble": true,
      "useMergedTexture": false,
      "visible": true,
      "width": 505,
      "x": 0,
      "y": 0,
      "adaptScreen": false,
      "backGroundImage": null,
      "backGroundImageData": null,
      "backGroundScale9Enable": false,
      "bgColorB": 255,
      "bgColorG": 200,
      "bgColorOpacity": 0,
      "bgColorR": 150,
      "bgEndColorB": 255,
      "bgEndColorG": 200,
      "bgEndColorR": 150,
      "bgStartColorB": 255,
      "bgStartColorG": 255,
      "bgStartColorR": 255,
      "capInsetsHeight": 1,
      "capInsetsWidth": 1,
      "capInsetsX": 0,
      "capInsetsY": 0,
      "clipAble": false,
      "colorType": 1,
      "layoutType": 0,
      "vectorX": 0,
      "vectorY": -0.5
    }
  }
}